condenser/__init__.py
condenser/query.py
condenser/utils.py
condenser-0.2.1.dist-info/LICENSE
condenser-0.2.1.dist-info/METADATA
condenser-0.2.1.dist-info/WHEEL
condenser-0.2.1.dist-info/top_level.txt
condenser-0.2.1.dist-info/RECORD
