Metadata-Version: 2.1
Name: condenser
Version: 0.2.1
Summary: A fast interface between SQLAlchemy and Numpy
Home-page: https://github.com/nens/condenser
Author: Casper van der Wel
Author-email: caspervdw@gmail.com
License: BSD license
Keywords: condenser
Classifier: Development Status :: 2 - Pre-Alpha
Classifier: Intended Audience :: Developers
Classifier: License :: OSI Approved :: BSD License
Classifier: Natural Language :: English
Classifier: Programming Language :: Python :: 3
Requires-Python: >=3.7
License-File: LICENSE
Requires-Dist: sqlalchemy (>=1.3)
Requires-Dist: numpy (>=1.15)
Provides-Extra: geo
Requires-Dist: geoalchemy2 (>=0.6) ; extra == 'geo'
Requires-Dist: shapely (>=2) ; extra == 'geo'
Provides-Extra: test
Requires-Dist: pytest (>=3) ; extra == 'test'
